bh_database/__init__.py
bh_database/base_table.py
bh_database/constant.py
bh_database/core.py
bh_database/paginator.py
bh_database-0.0.6.dist-info/METADATA
bh_database-0.0.6.dist-info/WHEEL
bh_database-0.0.6.dist-info/top_level.txt
bh_database-0.0.6.dist-info/RECORD
