Metadata-Version: 2.1
Name: bh-database
Version: 0.0.6
Summary: Database wrapper classes for SQLAlchemy.
Author-email: Van Be Hai Nguyen <behai_nguyen@hotmail.com>
Project-URL: repository, https://github.com/behai-nguyen/bh_database
Project-URL: documentation, https://bh-database.readthedocs.io/
Keywords: SQLAlchemy,database,wrapper
Classifier: License :: OSI Approved :: MIT License
Classifier: Programming Language :: Python
Classifier: Programming Language :: Python :: 3
Requires-Python: >=3.10
Requires-Dist: SQLAlchemy
Requires-Dist: bh-apistatus
Requires-Dist: bh-utils
Requires-Dist: tomli ; python_version >= "3.10"
Provides-Extra: builds
Requires-Dist: build ; extra == 'builds'
Requires-Dist: twine ; extra == 'builds'
Provides-Extra: dev
Requires-Dist: sphinx ; extra == 'dev'
Requires-Dist: myst-parser ; extra == 'dev'
Requires-Dist: sphinx-rtd-theme ; extra == 'dev'
Provides-Extra: mysql-connector-python
Requires-Dist: mysql-connector-python ; extra == 'mysql-connector-python'
Provides-Extra: psycopg2-binary
Requires-Dist: psycopg2-binary ; extra == 'psycopg2-binary'
Provides-Extra: tests
Requires-Dist: pytest ; extra == 'tests'
Requires-Dist: coverage ; extra == 'tests'
